ShExJSG/SchemaWithContext.py
ShExJSG/ShExC.py
ShExJSG/ShExJ.jsg
ShExJSG/ShExJ.py
ShExJSG/__init__.py
ShExJSG-0.8.2.dist-info/AUTHORS
ShExJSG-0.8.2.dist-info/LICENSE
ShExJSG-0.8.2.dist-info/METADATA
ShExJSG-0.8.2.dist-info/WHEEL
ShExJSG-0.8.2.dist-info/pbr.json
ShExJSG-0.8.2.dist-info/top_level.txt
ShExJSG-0.8.2.dist-info/RECORD
